sfcsim/__init__.py
sfcsim/algorithms/PSO_scheduler.py
sfcsim/algorithms/SA_scheduler.py
sfcsim/algorithms/TS_scheduler.py
sfcsim/algorithms/__init__.py
sfcsim/algorithms/common.py
sfcsim/algorithms/shortset_path_scheduler.py
sfcsim/algorithms/tempCodeRunnerFile.py
sfcsim/classes/__init__.py
sfcsim/classes/dynamic_traffic_sfc.py
sfcsim/classes/mobiel_sfc.py
sfcsim/classes/mobile_sfc.py
sfcsim/classes/network.py
sfcsim/classes/network_matrix.py
sfcsim/classes/node.py
sfcsim/classes/scheduler.py
sfcsim/classes/sfc.py
sfcsim/classes/vnf.py
sfcsim/layout/__init__.py
sfcsim/layout/cellular_layout.py
sfcsim/layout/cernnet2_layout.py
sfcsim/layout/nsfnet_layout.py
sfcsim/networks/__init__.py
sfcsim/networks/cernnet2.py
sfcsim/networks/nsfnet.py
sfcsim-1.0.8.dist-info/METADATA
sfcsim-1.0.8.dist-info/RECORD
sfcsim-1.0.8.dist-info/WHEEL
sfcsim-1.0.8.dist-info/top_level.txt
